trading_result_counter/__init__.py
trading_result_counter/main.py
trading_result_counter-0.1.dist-info/METADATA
trading_result_counter-0.1.dist-info/WHEEL
trading_result_counter-0.1.dist-info/top_level.txt
trading_result_counter-0.1.dist-info/RECORD
