Metadata-Version: 2.1
Name: trading-result-counter
Version: 0.1
Requires-Dist: pandas==2.2.2
